kuramoto/__init__.py
kuramoto/kuramoto.py
kuramoto/plotting.py
kuramoto-0.4.0.dist-info/licenses/LICENSE
kuramoto-0.4.0.dist-info/METADATA
kuramoto-0.4.0.dist-info/WHEEL
kuramoto-0.4.0.dist-info/top_level.txt
kuramoto-0.4.0.dist-info/RECORD
