Metadata-Version: 2.4
Name: kuramoto
Version: 0.4.0
Summary: Kuramoto model on graphs
Author-email: Fabrizio Damicelli <fabridamicelli@gmail.com>
License-Expression: MIT
Project-URL: Changelog, https://github.com/fabridamicelli/kuramoto/blob/main/CHANGELOG.md
Project-URL: Repository, https://github.com/fabridamicelli/kuramoto
Classifier: Operating System :: OS Independent
Classifier: Programming Language :: Python :: 3 :: Only
Classifier: Programming Language :: Python :: 3.9
Classifier: Programming Language :: Python :: 3.10
Classifier: Programming Language :: Python :: 3.11
Classifier: Programming Language :: Python :: 3.12
Classifier: Programming Language :: Python :: 3.13
Classifier: Intended Audience :: Science/Research
Classifier: Topic :: Scientific/Engineering
Requires-Python: >=3.9
License-File: LICENSE
Requires-Dist: numpy>=1.23.5
Requires-Dist: matplotlib
Requires-Dist: scipy
Dynamic: license-file
